throttle/__init__.py
throttle/cli.py
throttle/example.py
throttle/throttle.py
throttle_loader-0.1.0.dist-info/METADATA
throttle_loader-0.1.0.dist-info/WHEEL
throttle_loader-0.1.0.dist-info/entry_points.txt
throttle_loader-0.1.0.dist-info/top_level.txt
throttle_loader-0.1.0.dist-info/RECORD
