Metadata-Version: 2.1
Name: throttle-loader
Version: 0.1.0
Summary: A simple progress loader for Python
Home-page: https://github.com/bantoinese83/throttle
Author: Bryan Antoine
Author-email: b.antoine.se@gmail.com
Classifier: Programming Language :: Python :: 3
Classifier: License :: OSI Approved :: MIT License
Classifier: Operating System :: OS Independent
Requires-Python: >=3.6
